qdmap/__init__.py
qdmap/qdmap.py
qdmap-0.0.3.dist-info/LICENSE
qdmap-0.0.3.dist-info/METADATA
qdmap-0.0.3.dist-info/WHEEL
qdmap-0.0.3.dist-info/top_level.txt
qdmap-0.0.3.dist-info/RECORD
