Metadata-Version: 2.1
Name: qdmap
Version: 0.0.3
Summary: A python package for explosives safety quantity-distance spatial analysis.
Home-page: https://github.com/josh-spatial/qdmap
Author: Joshua Wustner
Author-email: wustner@gmail.com
License: MIT license
Keywords: qdmap
Classifier: Development Status :: 2 - Pre-Alpha
Classifier: Intended Audience :: Developers
Classifier: License :: OSI Approved :: MIT License
Classifier: Natural Language :: English
Classifier: Programming Language :: Python :: 3
Classifier: Programming Language :: Python :: 3.5
Classifier: Programming Language :: Python :: 3.6
Classifier: Programming Language :: Python :: 3.7
Classifier: Programming Language :: Python :: 3.8
Requires-Python: >=3.5
License-File: LICENSE
